pythontk/__init__.py
pythontk/core_utils/__init__.py
pythontk/core_utils/_core_utils.py
pythontk/core_utils/app_launcher.py
pythontk/core_utils/class_property.py
pythontk/core_utils/cli.py
pythontk/core_utils/git.py
pythontk/core_utils/help_mixin.py
pythontk/core_utils/hierarchy_diff.py
pythontk/core_utils/logging_mixin.py
pythontk/core_utils/module_reloader.py
pythontk/core_utils/module_resolver.py
pythontk/core_utils/namedtuple_container.py
pythontk/core_utils/namespace_handler.py
pythontk/core_utils/package_manager.py
pythontk/core_utils/singleton_mixin.py
pythontk/core_utils/execution_monitor/__init__.py
pythontk/core_utils/execution_monitor/_dialog_viewer.py
pythontk/core_utils/execution_monitor/_execution_monitor.py
pythontk/core_utils/execution_monitor/_gif_viewer.py
pythontk/core_utils/execution_monitor/task_indicator.gif
pythontk/core_utils/hierarchy_utils/__init__.py
pythontk/core_utils/hierarchy_utils/hierarchy_analyzer.py
pythontk/core_utils/hierarchy_utils/hierarchy_indexer.py
pythontk/core_utils/hierarchy_utils/hierarchy_matching.py
pythontk/core_utils/hierarchy_utils/backup/hierarchy_analyzer.py
pythontk/core_utils/hierarchy_utils/backup/hierarchy_indexer.py
pythontk/core_utils/hierarchy_utils/backup/hierarchy_matching.py
pythontk/file_utils/__init__.py
pythontk/file_utils/_file_utils.py
pythontk/file_utils/metadata.py
pythontk/img_utils/__init__.py
pythontk/img_utils/_img_utils.py
pythontk/img_utils/map_converter.py
pythontk/img_utils/map_converter.ui
pythontk/img_utils/map_factory.py
pythontk/img_utils/map_packer.py
pythontk/img_utils/map_packer.ui
pythontk/img_utils/map_registry.py
pythontk/iter_utils/__init__.py
pythontk/iter_utils/_iter_utils.py
pythontk/math_utils/__init__.py
pythontk/math_utils/_math_utils.py
pythontk/math_utils/progression.py
pythontk/net_utils/__init__.py
pythontk/net_utils/_net_utils.py
pythontk/net_utils/credentials.py
pythontk/net_utils/ssh_client.py
pythontk/str_utils/__init__.py
pythontk/str_utils/_str_utils.py
pythontk-0.7.71.dist-info/licenses/LICENSE
pythontk-0.7.71.dist-info/METADATA
pythontk-0.7.71.dist-info/WHEEL
pythontk-0.7.71.dist-info/top_level.txt
pythontk-0.7.71.dist-info/RECORD
