Metadata-Version: 2.4
Name: pythontk
Version: 0.7.71
Summary: A modular Python toolkit providing utilities for file handling, string processing, iteration, math operations, and more.
Author-email: Ryan Simpson <m3trik@outlook.com>
License: MIT
Project-URL: Homepage, https://github.com/m3trik/pythontk
Project-URL: Repository, https://github.com/m3trik/pythontk
Classifier: Programming Language :: Python :: 3
Classifier: License :: OSI Approved :: MIT License
Classifier: Operating System :: OS Independent
Requires-Python: >=3.9
License-File: LICENSE
Dynamic: license-file
